odin_slides/__init__.py
odin_slides/llm_ops.py
odin_slides/main.py
odin_slides/presentation.py
odin_slides/utils.py
tests/__init__.py
tests/test_presentation.py
tests/test_utils.py
odin_slides-0.9.dist-info/LICENSE
odin_slides-0.9.dist-info/METADATA
odin_slides-0.9.dist-info/WHEEL
odin_slides-0.9.dist-info/entry_points.txt
odin_slides-0.9.dist-info/top_level.txt
odin_slides-0.9.dist-info/RECORD
