Metadata-Version: 2.1
Name: odin-slides
Version: 0.9
Summary: An advanced Python tool that empowers you to effortlessly draft impressive PowerPoint presentations from Word documents using generative AI.
Home-page: https://github.com/leonid20000/odin-slides
Author: Dr. Leonit Zeynalvand
License: MIT
License-File: LICENSE
Requires-Dist: python-pptx
Requires-Dist: python-docx
Requires-Dist: requests
Requires-Dist: colorama
Requires-Dist: tqdm
